glm_mda_diffusion/__init__.py
glm_mda_diffusion/__main__.py
glm_mda_diffusion/glm_mda_diffusion.py
glm_mda_diffusion-1.1.dist-info/LICENSE
glm_mda_diffusion-1.1.dist-info/METADATA
glm_mda_diffusion-1.1.dist-info/WHEEL
glm_mda_diffusion-1.1.dist-info/top_level.txt
glm_mda_diffusion-1.1.dist-info/RECORD
