Metadata-Version: 2.1
Name: glm-mda-diffusion
Version: 1.1
Summary: Minimum dissipation approximation: A fast algorithm for the prediction of diffusive properties of intrinsically disordered proteins
Home-page: https://github.com/RadostW/glm-mda-diffusion/
Author: Radost Waszkiewicz
Author-email: radost.waszkiewicz@gmail.com
License: GNU GPLv3
Project-URL: Documentation, https://github.com/RadostW/glm_mda_diffusion
Project-URL: Source, https://github.com/RadostW/glm_mda_diffusion
Platform: UNKNOWN
License-File: LICENSE
Requires-Dist: numpy
Requires-Dist: pygrpy
Requires-Dist: sarw-spheres
Requires-Dist: scipy
